All_Process/Main.py
All_Process/Verifiers.py
All_Process/__init__.py
Simple_Password_Verificator-0.0.2.dist-info/METADATA
Simple_Password_Verificator-0.0.2.dist-info/WHEEL
Simple_Password_Verificator-0.0.2.dist-info/top_level.txt
Simple_Password_Verificator-0.0.2.dist-info/RECORD
