Metadata-Version: 2.1
Name: Simple_Password_Verificator
Version: 0.0.2
Summary: Pequeno sistema que valida a senha do usuário.
Home-page: https://github.com/Danieldantas7227
Author: Daniel Dantas Lopes
Author-email: dandantas29@gmail.com
Requires-Python: >=3.0
